dateparser/__init__.py
dateparser/__main__.py
dateparser/dateparser.py
dateparser/utils/COLORS.py
dateparser/utils/logger.py
bb_dateparser-0.2.43.dist-info/LICENSE
bb_dateparser-0.2.43.dist-info/METADATA
bb_dateparser-0.2.43.dist-info/WHEEL
bb_dateparser-0.2.43.dist-info/RECORD
