Metadata-Version: 2.1
Name: BB-DateParser
Version: 0.2.43
Summary: Try to parse date into a format for datetime
License: MIT
Keywords: utility,parser,datetime
Author: Erik Beebe
Requires-Python: >=3.10,<4.0
Classifier: License :: OSI Approved :: MIT License
Classifier: Programming Language :: Python :: 3
Classifier: Programming Language :: Python :: 3.10
Classifier: Programming Language :: Python :: 3.11
Requires-Dist: bb-apputils (>=0.4.0,<0.5.0)
